python_githooks/__init__.py
python_githooks/__main__.py
python_githooks/helpers.py
python_githooks/hook_template.py
python_githooks-1.0.7.dist-info/LICENSE
python_githooks-1.0.7.dist-info/METADATA
python_githooks-1.0.7.dist-info/WHEEL
python_githooks-1.0.7.dist-info/entry_points.txt
python_githooks-1.0.7.dist-info/top_level.txt
python_githooks-1.0.7.dist-info/RECORD
