Metadata-Version: 2.1
Name: python-githooks
Version: 1.0.7
Summary: Create git hooks with ease using a simple configuration file in a git project
Home-page: https://github.com/ygpedroso/python-githooks
Author: Yannier González Pedroso
Author-email: ygpedroso2503@gmail.com
License: MIT
Platform: UNKNOWN
Classifier: License :: OSI Approved :: MIT License
Classifier: Programming Language :: Python :: 3
Classifier: Intended Audience :: Developers
Classifier: Topic :: Software Development
License-File: LICENSE
Requires-Dist: configparser
